{"errors":[],"warnings":[],"namedChunkGroups":{"polyfill":{"chunks":[2,0,7],"assets":["webpack-runtime-11236cc4e133606a2060.js","webpack-runtime-11236cc4e133606a2060.js.map","commons-1b5f3101d14b8c1e6e49.js","commons-1b5f3101d14b8c1e6e49.js.map","polyfill-5acc46d2c6294ee52fa0.js","polyfill-5acc46d2c6294ee52fa0.js.map"],"children":{},"childAssets":{}},"app":{"chunks":[2,6,0,3],"assets":["webpack-runtime-11236cc4e133606a2060.js","webpack-runtime-11236cc4e133606a2060.js.map","framework-d066f55745d479a55fde.js","framework-d066f55745d479a55fde.js.map","commons-1b5f3101d14b8c1e6e49.js","commons-1b5f3101d14b8c1e6e49.js.map","app-6408d4e5a95aeb1ad9ba.js","app-6408d4e5a95aeb1ad9ba.js.map"],"children":{},"childAssets":{}},"component---src-pages-404-js":{"chunks":[1,0,4],"assets":["styles.917e5e8be6ae66dc6a4b.css","styles-e9d24b1846c7d6eb9685.js","styles-e9d24b1846c7d6eb9685.js.map","commons-1b5f3101d14b8c1e6e49.js","commons-1b5f3101d14b8c1e6e49.js.map","component---src-pages-404-js-6a287b247abd7b7d5447.js","component---src-pages-404-js-6a287b247abd7b7d5447.js.map"],"children":{},"childAssets":{}},"component---src-pages-index-js":{"chunks":[1,0,5],"assets":["styles.917e5e8be6ae66dc6a4b.css","styles-e9d24b1846c7d6eb9685.js","styles-e9d24b1846c7d6eb9685.js.map","commons-1b5f3101d14b8c1e6e49.js","commons-1b5f3101d14b8c1e6e49.js.map","component---src-pages-index-js-9ce742448be8f37cd979.js","component---src-pages-index-js-9ce742448be8f37cd979.js.map"],"children":{},"childAssets":{}}},"assetsByChunkName":{"polyfill":["webpack-runtime-11236cc4e133606a2060.js","commons-1b5f3101d14b8c1e6e49.js","polyfill-5acc46d2c6294ee52fa0.js"],"app":["webpack-runtime-11236cc4e133606a2060.js","framework-d066f55745d479a55fde.js","commons-1b5f3101d14b8c1e6e49.js","app-6408d4e5a95aeb1ad9ba.js"],"component---src-pages-404-js":["styles.917e5e8be6ae66dc6a4b.css","styles-e9d24b1846c7d6eb9685.js","commons-1b5f3101d14b8c1e6e49.js","component---src-pages-404-js-6a287b247abd7b7d5447.js"],"component---src-pages-index-js":["styles.917e5e8be6ae66dc6a4b.css","styles-e9d24b1846c7d6eb9685.js","commons-1b5f3101d14b8c1e6e49.js","component---src-pages-index-js-9ce742448be8f37cd979.js"]}}